MofanPythonJiaocheng2017510/README.md
MofanPythonJiaocheng2017510/__init__.py
MofanPythonJiaocheng2017510/__main__.py
MofanPythonJiaocheng2017510/file.epub
MofanPythonJiaocheng2017510/index.html
MofanPythonJiaocheng2017510/css/__init__.py
MofanPythonJiaocheng2017510/css/annotations.css
MofanPythonJiaocheng2017510/css/main.css
MofanPythonJiaocheng2017510/css/normalize.css
MofanPythonJiaocheng2017510/css/popup.css
MofanPythonJiaocheng2017510/font/__init__.py
MofanPythonJiaocheng2017510/font/fontello.eot
MofanPythonJiaocheng2017510/font/fontello.svg
MofanPythonJiaocheng2017510/font/fontello.ttf
MofanPythonJiaocheng2017510/font/fontello.woff
MofanPythonJiaocheng2017510/img/__init__.py
MofanPythonJiaocheng2017510/img/annotator-glyph-sprite.png
MofanPythonJiaocheng2017510/img/annotator-icon-sprite.png
MofanPythonJiaocheng2017510/img/apple-touch-icon.png
MofanPythonJiaocheng2017510/img/cancelfullscreen.png
MofanPythonJiaocheng2017510/img/close.png
MofanPythonJiaocheng2017510/img/fullscreen.png
MofanPythonJiaocheng2017510/img/loader.gif
MofanPythonJiaocheng2017510/img/menu-icon.png
MofanPythonJiaocheng2017510/img/save.png
MofanPythonJiaocheng2017510/img/saved.png
MofanPythonJiaocheng2017510/img/settings-s.png
MofanPythonJiaocheng2017510/img/settings.png
MofanPythonJiaocheng2017510/img/star.png
MofanPythonJiaocheng2017510/js/__init__.py
MofanPythonJiaocheng2017510/js/epub.js
MofanPythonJiaocheng2017510/js/epub.min.js
MofanPythonJiaocheng2017510/js/epub.min.map
MofanPythonJiaocheng2017510/js/hooks.min.js
MofanPythonJiaocheng2017510/js/hooks.min.map
MofanPythonJiaocheng2017510/js/reader.js
MofanPythonJiaocheng2017510/js/reader.js.map
MofanPythonJiaocheng2017510/js/reader.min.js
MofanPythonJiaocheng2017510/js/reader.min.map
MofanPythonJiaocheng2017510/js/hooks/__init__.py
MofanPythonJiaocheng2017510/js/hooks/extensions/__init__.py
MofanPythonJiaocheng2017510/js/hooks/extensions/highlight.js
MofanPythonJiaocheng2017510/js/libs/__init__.py
mofan_python_jiaocheng_2017_5_10-2024.3.2.0.dist-info/METADATA
mofan_python_jiaocheng_2017_5_10-2024.3.2.0.dist-info/WHEEL
mofan_python_jiaocheng_2017_5_10-2024.3.2.0.dist-info/entry_points.txt
mofan_python_jiaocheng_2017_5_10-2024.3.2.0.dist-info/top_level.txt
mofan_python_jiaocheng_2017_5_10-2024.3.2.0.dist-info/RECORD
